uproot4/__init__.py
uproot4-4.0.0.dist-info/LICENSE
uproot4-4.0.0.dist-info/METADATA
uproot4-4.0.0.dist-info/WHEEL
uproot4-4.0.0.dist-info/top_level.txt
uproot4-4.0.0.dist-info/RECORD
